flake8_length/__init__.py
flake8_length/__main__.py
flake8_length/_checker.py
flake8_length/_cli.py
flake8_length/_parser.py
flake8_length-0.3.1.dist-info/entry_points.txt
flake8_length-0.3.1.dist-info/LICENSE
flake8_length-0.3.1.dist-info/WHEEL
flake8_length-0.3.1.dist-info/METADATA
flake8_length-0.3.1.dist-info/RECORD
