Metadata-Version: 2.1
Name: flake8-length
Version: 0.3.1
Summary: Flake8 plugin for a smart line length validation.
Home-page: https://github.com/orsinium-labs/flake8-length
License: MIT
Keywords: flake8,plugins,introspection,linter
Author: Gram
Author-email: gram@orsinium.dev
Requires-Python: >=3.6
Classifier: Development Status :: 5 - Production/Stable
Classifier: Environment :: Plugins
Classifier: Intended Audience :: Developers
Classifier: License :: OSI Approved :: MIT License
Classifier: Programming Language :: Python
Classifier: Topic :: Software Development
Classifier: Topic :: Software Development :: Quality Assurance
Requires-Dist: flake8
Requires-Dist: isort ; extra == "dev"
Requires-Dist: mypy ; extra == "dev"
Requires-Dist: pytest ; extra == "dev"
Provides-Extra: dev
